pyboot/dataflow/__init__.py
pyboot/dataflow/boot.py
pyboot/dataflow/main.py
pyboot/dataflow/module/__init__.py
pyboot/dataflow/router/endpoint.py
pyboot/dataflow/utils/web/asgi.py
pyboot/dataflow/utils/web/asgi_proxy.py
pyboot_dataflow-1.3.3.dist-info/licenses/LICENSE
pyboot_dataflow-1.3.3.dist-info/METADATA
pyboot_dataflow-1.3.3.dist-info/WHEEL
pyboot_dataflow-1.3.3.dist-info/top_level.txt
pyboot_dataflow-1.3.3.dist-info/RECORD
