Metadata-Version: 2.4
Name: pyboot-dataflow
Version: 1.3.3
Summary: Pyboot-dataflow is an open-source Python microservice framework that simplifies the development of stand-alone production-grade Spring applications.
Author-email: joinsunsoft <793875613@qq.com>
Maintainer-email: joinsunsoft <inthirties.liu@hotmail.com>
License-Expression: Apache-2.0
Project-URL: Homepage, https://gitee.com/pyboot/pyboot-dataflow
Project-URL: Repository, https://gitee.com/pyboot/pyboot-dataflow
Project-URL: Issues, https://gitee.com/pyboot/pyboot-dataflow
Keywords: web,framework,cli,springboot,fastapi
Classifier: Development Status :: 4 - Beta
Classifier: Intended Audience :: Developers
Classifier: Operating System :: OS Independent
Classifier: Programming Language :: Python :: 3
Classifier: Programming Language :: Python :: 3.8
Classifier: Programming Language :: Python :: 3.9
Classifier: Programming Language :: Python :: 3.10
Classifier: Programming Language :: Python :: 3.11
Classifier: Programming Language :: Python :: 3.12
Classifier: Topic :: Software Development :: Libraries :: Application Frameworks
Requires-Python: >=3.12.10
License-File: LICENSE
Requires-Dist: fastapi==0.120.4
Requires-Dist: httpx==0.28.1
Requires-Dist: pyboot-commons-utils
Requires-Dist: typing_extensions==4.15.0
Requires-Dist: uvicorn==0.38.0
Dynamic: license-file
